odoo/addons/l10n_it_asset_history_import_queue/README.rst
odoo/addons/l10n_it_asset_history_import_queue/__init__.py
odoo/addons/l10n_it_asset_history_import_queue/__manifest__.py
odoo/addons/l10n_it_asset_history_import_queue/data/data.xml
odoo/addons/l10n_it_asset_history_import_queue/i18n/it.po
odoo/addons/l10n_it_asset_history_import_queue/i18n/l10n_it_asset_history_import_queue.pot
odoo/addons/l10n_it_asset_history_import_queue/readme/CONTRIBUTORS.rst
odoo/addons/l10n_it_asset_history_import_queue/readme/DESCRIPTION.rst
odoo/addons/l10n_it_asset_history_import_queue/static/description/icon.png
odoo/addons/l10n_it_asset_history_import_queue/static/description/index.html
odoo/addons/l10n_it_asset_history_import_queue/wizard/__init__.py
odoo/addons/l10n_it_asset_history_import_queue/wizard/asset_history_import.py
odoo14_addon_l10n_it_asset_history_import_queue-14.0.1.0.1.dev5.dist-info/METADATA
odoo14_addon_l10n_it_asset_history_import_queue-14.0.1.0.1.dev5.dist-info/WHEEL
odoo14_addon_l10n_it_asset_history_import_queue-14.0.1.0.1.dev5.dist-info/top_level.txt
odoo14_addon_l10n_it_asset_history_import_queue-14.0.1.0.1.dev5.dist-info/RECORD
