Metadata-Version: 2.1
Name: odoo14-addon-l10n-it-asset-history-import-queue
Version: 14.0.1.0.1.dev5
Summary: Cespiti: importazione storico dati in background
Home-page: https://github.com/OCA/l10n-italy
Author: Ooops,Odoo Community Association (OCA)
Author-email: support@odoo-community.org
License: AGPL-3
Platform: UNKNOWN
Classifier: Programming Language :: Python
Classifier: Framework :: Odoo
Classifier: Framework :: Odoo :: 14.0
Classifier: License :: OSI Approved :: GNU Affero General Public License v3
Classifier: Development Status :: 4 - Beta
Requires-Python: >=3.6
Requires-Dist: odoo14-addon-l10n-it-asset-history-import
Requires-Dist: odoo14-addon-queue-job
Requires-Dist: odoo14-addon-web-notify
Requires-Dist: odoo <14.1dev,>=14.0a
